README.md
setup.py
celoetl/__init__.py
celoetl/__main__.py
celoetl/atomic_counter.py
celoetl/csv_utils.py
celoetl/erc20_abi.py
celoetl/exporters.py
celoetl/json_rpc_requests.py
celoetl/misc_utils.py
celoetl/progress_logger.py
celoetl/thread_local_proxy.py
celoetl/utils.py
celoetl/cli/__init__.py
celoetl/cli/export_all.py
celoetl/cli/export_blocks_and_transactions.py
celoetl/cli/export_geth_traces.py
celoetl/cli/export_receipts_and_logs.py
celoetl/cli/extract_contracts.py
celoetl/cli/extract_csv_column.py
celoetl/cli/extract_geth_traces.py
celoetl/cli/extract_token_transfers.py
celoetl/cli/extract_tokens.py
celoetl/cli/get_block_range_for_date.py
celoetl/cli/get_block_range_for_timestamps.py
celoetl/cli/rate_limiting_proxy.py
celoetl/cli/stream.py
celoetl/domain/__init__.py
celoetl/domain/block.py
celoetl/domain/contract.py
celoetl/domain/geth_trace.py
celoetl/domain/receipt.py
celoetl/domain/receipt_log.py
celoetl/domain/token.py
celoetl/domain/token_transfer.py
celoetl/domain/trace.py
celoetl/domain/transaction.py
celoetl/enumeration/__init__.py
celoetl/enumeration/entity_type.py
celoetl/executors/__init__.py
celoetl/executors/batch_work_executor.py
celoetl/executors/bounded_executor.py
celoetl/executors/fail_safe_executor.py
celoetl/jobs/__init__.py
celoetl/jobs/export_all_common.py
celoetl/jobs/export_blocks_job.py
celoetl/jobs/export_geth_traces_job.py
celoetl/jobs/export_receipts_job.py
celoetl/jobs/export_tokens_job.py
celoetl/jobs/extract_contracts_job.py
celoetl/jobs/extract_geth_traces_job.py
celoetl/jobs/extract_token_transfers_job.py
celoetl/jobs/extract_tokens_job.py
celoetl/jobs/exporters/__init__.py
celoetl/jobs/exporters/blocks_and_transactions_item_exporter.py
celoetl/jobs/exporters/contracts_item_exporter.py
celoetl/jobs/exporters/geth_traces_item_exporter.py
celoetl/jobs/exporters/receipts_and_logs_item_exporter.py
celoetl/jobs/exporters/token_transfers_item_exporter.py
celoetl/jobs/exporters/tokens_item_exporter.py
nansen_celo_etl.egg-info/PKG-INFO
nansen_celo_etl.egg-info/SOURCES.txt
nansen_celo_etl.egg-info/dependency_links.txt
nansen_celo_etl.egg-info/entry_points.txt
nansen_celo_etl.egg-info/requires.txt
nansen_celo_etl.egg-info/top_level.txt