Metadata-Version: 2.1
Name: nansen-celo-etl
Version: 0.0.1
Summary: Tools for exporting Celo blockchain data to CSV or JSON
Home-page: https://github.com/nansen-ai/celo-etl
Author: Evgeny Medvedev
Author-email: evge.medvedev@gmail.com
License: UNKNOWN
Project-URL: Bug Reports, https://github.com/nansen-ai/celo-etl/issues
Project-URL: Source, https://github.com/nansen-ai/celo-etl
Keywords: evm
Platform: UNKNOWN
Classifier: Development Status :: 5 - Production/Stable
Classifier: Intended Audience :: Developers
Classifier: License :: OSI Approved :: MIT License
Classifier: Programming Language :: Python :: 3
Classifier: Programming Language :: Python :: 3.5
Classifier: Programming Language :: Python :: 3.6
Classifier: Programming Language :: Python :: 3.7
Classifier: Programming Language :: Python :: 3.8
Requires-Python: >=3.5.3,<4
Provides-Extra: streaming
Provides-Extra: dev
